{
  "version": "7",
  "dialect": "mysql",
  "entries": [
    {
      "idx": 0,
      "version": "5",
      "when": 1776014812872,
      "tag": "0000_silky_mandroid",
      "breakpoints": true
    },
    {
      "idx": 1,
      "version": "5",
      "when": 1776014984257,
      "tag": "0001_chubby_blue_shield",
      "breakpoints": true
    },
    {
      "idx": 2,
      "version": "5",
      "when": 1776200000000,
      "tag": "0002_omnichannel_expansion",
      "breakpoints": true
    },
    {
      "idx": 3,
      "version": "5",
      "when": 1776119922092,
      "tag": "0003_last_mariko_yashida",
      "breakpoints": true
    }
  ]
}